quickscreen/__init__.py
quickscreen/analysis/__init__.py
quickscreen/analysis/datafill.py
quickscreen/analysis/linear_analysis.py
quickscreen/plot/__init__.py
quickscreen/plot/grapher.py
quickscreen/plot/plotter.py
quickscreen/summary/__init__.py
quickscreen/summary/summary_classes.py
quickscreen/summary/summary_stats.py
quickscreen-0.2.dist-info/LICENSE.MD
quickscreen-0.2.dist-info/METADATA
quickscreen-0.2.dist-info/WHEEL
quickscreen-0.2.dist-info/top_level.txt
quickscreen-0.2.dist-info/RECORD
