Metadata-Version: 2.1
Name: quickscreen
Version: 0.2
Summary: A package for exploring data
Home-page: https://github.com/mqharris/533_lab2
Author: Nathan Smith, Mitch Harris, Ryan Koenig
Author-email: mitchharris@live.ca
License: MIT
Platform: UNKNOWN
Requires-Dist: pandas
Requires-Dist: numpy
Requires-Dist: matplotlib
Requires-Dist: seaborn
Requires-Dist: scikit-learn
